stupidtree/__init__.py
stupidtree/core/__init__.py
stupidtree/core/base_tree.py
stupidtree/core/indexed_tree.py
stupidtree/core/indexer.py
stupidtree/core/indexer_test.py
stupidtree/core/node.py
stupidtree/core/node_test.py
stupidtree/examples/__init__.py
stupidtree/examples/address/__init__.py
stupidtree/examples/address/level.py
stupidtree/examples/address/level_test.py
stupidtree/examples/address/node.py
stupidtree/examples/address/node_test.py
stupidtree/examples/address/pcd_tree.py
stupidtree/examples/address/pcd_tree_test.py
stupidtree-0.1.0.dist-info/METADATA
stupidtree-0.1.0.dist-info/RECORD
stupidtree-0.1.0.dist-info/WHEEL
stupidtree-0.1.0.dist-info/top_level.txt
