Metadata-Version: 2.1
Name: stupidtree
Version: 0.1.0
Summary: A generic tree implementation in Python.
Home-page: https://github.com/luozhouyang/stupidtree
Author: ZhouYang Luo
Author-email: stupidme.me.lzy@gmail.com
License: MIT License
Platform: UNKNOWN
Classifier: Programming Language :: Python :: 3
Classifier: License :: OSI Approved :: MIT License
Classifier: Operating System :: OS Independent
